dbbs_models/__init__.py
dbbs_models/basket_cell_models.py
dbbs_models/golgi_cell_models.py
dbbs_models/granule_cell_models.py
dbbs_models/purkinje_cell_models.py
dbbs_models/stellate_cell_models.py
dbbs_models/morphologies/BasketCell.swc
dbbs_models/morphologies/GolgiCell.asc
dbbs_models/morphologies/GolgiCell.swc
dbbs_models/morphologies/GranuleCell.swc
dbbs_models/morphologies/PurkinjeCell.swc
dbbs_models/morphologies/StellateCell.swc
dbbs_models/test/__init__.py
dbbs_models-6.0.0.dist-info/licenses/LICENSE
dbbs_models-6.0.0.dist-info/WHEEL
dbbs_models-6.0.0.dist-info/METADATA
dbbs_models-6.0.0.dist-info/RECORD
