Metadata-Version: 2.4
Name: dbbs-models
Version: 6.0.0
Summary: Collection of single cell models for the Arbor and NEURON simulators of the cerebellar
Author-email: Robin De Schepper <robingilbert.deschepper@unipv.it>
Classifier: License :: OSI Approved :: GNU General Public License v3 or later (GPLv3+)
License-File: LICENSE
Requires-Dist: arborize[neuron]~=6.0
Requires-Dist: dbbs-catalogue~=6.0
Requires-Dist: coverage~=7.3 ; extra == "test"
Project-URL: Home, https://github.com/dbbs-lab/models
Provides-Extra: test
